myprintfade/__init__.py
myprintfade/animation.py
myprintfade-0.2.dist-info/METADATA
myprintfade-0.2.dist-info/WHEEL
myprintfade-0.2.dist-info/top_level.txt
myprintfade-0.2.dist-info/RECORD
