Metadata-Version: 2.1
Name: myprintfade
Version: 0.2
Summary: Text Animations for Python Printing
